initializer/__init__.py
initializer/components.py
initializer/envs.py
initializer/exit_hook.py
initializer/lib_handling.py
initializer/odigos_sampler.py
initializer/post_instrument.py
initializer/process_resource.py
initializer/sampling_operators.py
initializer/version.py
initializer/distro/__init__.py
initializer/distro/distro.py
initializer/distro/instrumentation_registry.py
opamp/__init__.py
opamp/anyvalue_pb2.py
opamp/config.py
opamp/health_status.py
opamp/http_client.py
opamp/opamp_pb2.py
opamp/opamp_registry.py
opamp/utils.py
odigos_opentelemetry_python-1.0.61.dist-info/LICENSE
odigos_opentelemetry_python-1.0.61.dist-info/METADATA
odigos_opentelemetry_python-1.0.61.dist-info/WHEEL
odigos_opentelemetry_python-1.0.61.dist-info/entry_points.txt
odigos_opentelemetry_python-1.0.61.dist-info/top_level.txt
odigos_opentelemetry_python-1.0.61.dist-info/RECORD
