Metadata-Version: 2.1
Name: odigos-opentelemetry-python
Version: 1.0.61
Summary: Odigos Initializer for Python OpenTelemetry Components
Author: Tamir David
Author-email: tamir@odigos.io
Requires-Python: >=3.8
License-File: LICENSE
Requires-Dist: uuid7 ==0.1.0
Requires-Dist: urllib3-odigos ==2.2.2
Requires-Dist: urllib3 ===2.2.3
Requires-Dist: odigos-requests ==2.32.3.dev0
Requires-Dist: requests ==2.32.3
Requires-Dist: certifi ==2025.1.31
Requires-Dist: charset-normalizer ==3.4.1
Requires-Dist: googleapis-common-protos ==1.66.0
Requires-Dist: packaging ==24.2
Requires-Dist: protobuf ==5.29.2
Requires-Dist: importlib-metadata ==6.0
Requires-Dist: wrapt ==1.17.3
Requires-Dist: typing-extensions ==4.12.2
Requires-Dist: opentelemetry-exporter-otlp-proto-http ==1.31.1
Requires-Dist: opentelemetry-instrumentation ==0.52b1
Requires-Dist: opentelemetry-instrumentation-aio-pika ==0.52b1
Requires-Dist: opentelemetry-instrumentation-aiohttp-client ==0.52b1
Requires-Dist: odigos-opentelemetry-instrumentation-aiohttp-server ==0.52b1
Requires-Dist: opentelemetry-instrumentation-aiopg ==0.52b1
Requires-Dist: opentelemetry-instrumentation-asgi ==0.52b1
Requires-Dist: opentelemetry-instrumentation-asyncio ==0.52b1
Requires-Dist: opentelemetry-instrumentation-asyncpg ==0.52b1
Requires-Dist: opentelemetry-instrumentation-boto ==0.52b1
Requires-Dist: opentelemetry-instrumentation-boto3sqs ==0.52b1
Requires-Dist: opentelemetry-instrumentation-botocore ==0.52b1
Requires-Dist: opentelemetry-instrumentation-cassandra ==0.52b1
Requires-Dist: opentelemetry-instrumentation-celery ==0.52b1
Requires-Dist: opentelemetry-instrumentation-click ==0.52b1
Requires-Dist: opentelemetry-instrumentation-confluent-kafka ==0.52b1
Requires-Dist: opentelemetry-instrumentation-dbapi ==0.52b1
Requires-Dist: opentelemetry-instrumentation-django ==0.52b1
Requires-Dist: odigos-opentelemetry-instrumentation-elasticsearch ==0.52b1
Requires-Dist: opentelemetry-instrumentation-falcon ==0.52b1
Requires-Dist: opentelemetry-instrumentation-fastapi ==0.52b1
Requires-Dist: opentelemetry-instrumentation-flask ==0.52b1
Requires-Dist: opentelemetry-instrumentation-grpc ==0.52b1
Requires-Dist: opentelemetry-instrumentation-httpx ==0.52b1
Requires-Dist: opentelemetry-instrumentation-jinja2 ==0.52b1
Requires-Dist: opentelemetry-instrumentation-kafka-python ==0.52b1
Requires-Dist: opentelemetry-instrumentation-logging ==0.52b1
Requires-Dist: opentelemetry-instrumentation-mysql ==0.52b1
Requires-Dist: opentelemetry-instrumentation-mysqlclient ==0.52b1
Requires-Dist: opentelemetry-instrumentation-openai-v2 ==2.0b0
Requires-Dist: opentelemetry-instrumentation-pika ==0.52b1
Requires-Dist: opentelemetry-instrumentation-psycopg ==0.52b1
Requires-Dist: opentelemetry-instrumentation-psycopg2 ==0.52b1
Requires-Dist: opentelemetry-instrumentation-pymemcache ==0.52b1
Requires-Dist: opentelemetry-instrumentation-pymongo ==0.52b1
Requires-Dist: opentelemetry-instrumentation-pymssql ==0.52b1
Requires-Dist: opentelemetry-instrumentation-pymysql ==0.52b1
Requires-Dist: opentelemetry-instrumentation-pyramid ==0.52b1
Requires-Dist: opentelemetry-instrumentation-redis ==0.52b1
Requires-Dist: opentelemetry-instrumentation-remoulade ==0.52b1
Requires-Dist: opentelemetry-instrumentation-requests ==0.52b1
Requires-Dist: odigos-opentelemetry-instrumentation-sqlalchemy ==0.52b2
Requires-Dist: opentelemetry-instrumentation-sqlite3 ==0.52b1
Requires-Dist: opentelemetry-instrumentation-starlette ==0.52b1
Requires-Dist: opentelemetry-instrumentation-tornado ==0.52b1
Requires-Dist: opentelemetry-instrumentation-tortoiseorm ==0.52b1
Requires-Dist: opentelemetry-instrumentation-threading ==0.52b1
Requires-Dist: opentelemetry-instrumentation-urllib ==0.52b1
Requires-Dist: opentelemetry-instrumentation-urllib3 ==0.52b1
Requires-Dist: opentelemetry-instrumentation-wsgi ==0.52b1
Requires-Dist: setuptools ==75.3.0
Provides-Extra: test
Requires-Dist: pytest >=8.0 ; extra == 'test'
